pydevcli/__init__.py
pydevcli/__main__.py
pydevcli/cli.py
pydevcli/images/__init__.py
pydevcli/images/cli.py
pydevcli/images/convert.py
pydevcli/images/website.py
pydevcli/util/__init__.py
pydevcli/util/cli.py
pydevcli/util/secrets.py
pydevcli2-0.2.0.dist-info/METADATA
pydevcli2-0.2.0.dist-info/WHEEL
pydevcli2-0.2.0.dist-info/entry_points.txt
pydevcli2-0.2.0.dist-info/RECORD
