Metadata-Version: 2.1
Name: pydevcli2
Version: 0.2.0
Summary: Python CLI for various purposes
License: MIT
Author: giraycoskun
Author-email: giraycoskun.dev@gmail.com
Requires-Python: >=3.11,<4.0
Classifier: License :: OSI Approved :: MIT License
Classifier: Programming Language :: Python :: 3
Classifier: Programming Language :: Python :: 3.11
Classifier: Programming Language :: Python :: 3.12
Requires-Dist: typer[all] (>=0.9.0,<0.10.0)
